LICENSE
aidd_codebase/__init__.py
aidd_codebase/datamodules/__init__.py
aidd_codebase/framework/__init__.py
aidd_codebase/framework/initiator.py
aidd_codebase/framework/loggers.py
aidd_codebase/models/__init__.py
aidd_codebase/models/modules/__init__.py
aidd_codebase/models/net_classifier.py
aidd_codebase/new_project/__init__.py
aidd_codebase/new_project/main.py
aidd_codebase/new_project/src/__init__.py
aidd_codebase/registries.py
aidd_codebase/start_project.py
aidd_codebase/utils/__init__.py
aidd_codebase/utils/callbacks.py
aidd_codebase/utils/config_checker.py
aidd_codebase/utils/device.py
aidd_codebase/utils/helper_functions.py
aidd_codebase/utils/setup.py
aidd_codebase/utils/tools.py
aidd_codebase/utils/typescripts.py
aidd_codebase-0.2.0.dist-info/LICENSE
aidd_codebase-0.2.0.dist-info/WHEEL
aidd_codebase-0.2.0.dist-info/METADATA
aidd_codebase-0.2.0.dist-info/RECORD
