Metadata-Version: 2.1
Name: aidd-codebase
Version: 0.2.0
Summary: High-level codebase for deep learning development in drug discovery.
Home-page: https://github.com/aidd-msca/aidd-codebase
License: MIT
Keywords: aidd,drug discovery,deep learning
Author: Peter Hartog
Author-email: peter.hartog@hotmail.nl
Requires-Python: >=3.7,<4.0
Classifier: Development Status :: 2 - Pre-Alpha
Classifier: Environment :: GPU :: NVIDIA CUDA :: 11.4
Classifier: License :: OSI Approved :: MIT License
Classifier: Programming Language :: Python :: 3
Classifier: Programming Language :: Python :: 3.10
Classifier: Programming Language :: Python :: 3.7
Classifier: Programming Language :: Python :: 3.8
Classifier: Programming Language :: Python :: 3.9
Classifier: Topic :: Scientific/Engineering :: Artificial Intelligence
Requires-Dist: tensorboard (>=2.6,<3.0)
Requires-Dist: wandb (>=0.12.16,<0.13.0)
Project-URL: Repository, https://github.com/aidd-msca/aidd-codebase
